{
  "101": "{userName} created an account{date}.",
  "102": "{userName} signed in{date}.",
  "103": "{userName} signed out{date}.",
  "104": "{userName} requested a password reset{date}.",

  "110": "{userName} deactivated their account{date}.",
  "111": "{userName} reactivated their account{date}.",
  
  "120": "{userName} updated their profile{date}.",
  
  "130": "{userName} updated settings{date}.",
  
  "140": "{userName} is now friends with {friendName}{date}.",

  "200": "{userName} performed an atlas action{date}.",

  "210": "{userName} saved overlays{date}.",
  "211": "{userName} added an overlay '{itemName}'{date}.",
  "212": "{userName} edited an overlay '{itemName}'{date}.",
  "213": "{userName} removed an overlay '{itemName}'{date}.",
  "214": "{userName} reordered overlays{date}.",

  "220": "{userName} saved markers{date}.",
  "221": "{userName} added a marker '{itemName}'{location}{date}.",
  "222": "{userName} edited a marker '{itemName}'{location}{date}.",
  "223": "{userName} removed a marker '{itemName}'{location}{date}.",

  "400": "{userName} performed a trips action{date}.",

  "410": "{userName} saved trips{date}.",
  "411": "{userName} added a trip '{itemName}'{date}.",
  "412": "{userName} edited a trip '{itemName}'{date}.",  
  "413": "{userName} {action} a trip '{itemName}'{date}.",
  "414": "{userName} rated a trip '{itemName}'{date}.",
  "415": "{userName} removed a trip '{itemName}'{date}."
}
